PyBrowserID-0.14.0.dist-info/DESCRIPTION.rst
PyBrowserID-0.14.0.dist-info/METADATA
PyBrowserID-0.14.0.dist-info/RECORD
PyBrowserID-0.14.0.dist-info/WHEEL
PyBrowserID-0.14.0.dist-info/metadata.json
PyBrowserID-0.14.0.dist-info/top_level.txt
browserid/__init__.py
browserid/errors.py
browserid/jwt.py
browserid/netutils.py
browserid/supportdoc.py
browserid/utils.py
browserid/crypto/__init__.py
browserid/crypto/_m2_monkeypatch.py
browserid/crypto/fallback.py
browserid/crypto/m2.py
browserid/tests/__init__.py
browserid/tests/support.py
browserid/tests/test_jwt.py
browserid/tests/test_m2_monkeypatch.py
browserid/tests/test_supportdoc.py
browserid/tests/test_utils.py
browserid/tests/test_verifiers.py
browserid/verifiers/__init__.py
browserid/verifiers/local.py
browserid/verifiers/remote.py
browserid/verifiers/workerpool.py
