Metadata-Version: 2.0
Name: PyBrowserID
Version: 0.14.0
Summary: Python library for the BrowserID Protocol
Home-page: https://github.com/mozilla/PyBrowserID
Author: Mozilla Identity Team
Author-email: dev-identity@lists.mozilla.org
License: MPLv2.0
Keywords: authentication browserid login email
Platform: UNKNOWN
Classifier: Programming Language :: Python
Classifier: Programming Language :: Python :: 2
Classifier: Programming Language :: Python :: 3
Classifier: Development Status :: 4 - Beta
Classifier: License :: OSI Approved :: Mozilla Public License 2.0 (MPL 2.0)
Requires-Dist: requests
